adk_middleware/__init__.py
adk_middleware/adk_agent.py
adk_middleware/agent_registry.py
adk_middleware/client_proxy_tool.py
adk_middleware/client_proxy_toolset.py
adk_middleware/endpoint.py
adk_middleware/event_translator.py
adk_middleware/execution_state.py
adk_middleware/session_manager.py
adk_middleware/utils/__init__.py
adk_middleware/utils/converters.py
ag_ui_adk_middleware-0.2.2.dist-info/METADATA
ag_ui_adk_middleware-0.2.2.dist-info/WHEEL
ag_ui_adk_middleware-0.2.2.dist-info/top_level.txt
ag_ui_adk_middleware-0.2.2.dist-info/RECORD
