Metadata-Version: 2.2
Name: ag-ui-adk-middleware
Version: 0.2.2
Summary: ADK Middleware for AG-UI Protocol - Bridge Google ADK agents with AG-UI
Home-page: https://github.com/ag-ui-protocol/ag-ui-protocol
Author: AG-UI Protocol Contributors
Classifier: Development Status :: 3 - Alpha
Classifier: Intended Audience :: Developers
Classifier: Topic :: Software Development :: Libraries :: Python Modules
Classifier: License :: OSI Approved :: MIT License
Classifier: Programming Language :: Python :: 3
Classifier: Programming Language :: Python :: 3.8
Classifier: Programming Language :: Python :: 3.9
Classifier: Programming Language :: Python :: 3.10
Classifier: Programming Language :: Python :: 3.11
Requires-Python: >=3.8
Requires-Dist: ag-ui-protocol>=0.1.7
Requires-Dist: google-adk>=1.6.1
Requires-Dist: pydantic>=2.11.7
Requires-Dist: asyncio>=3.4.3
Requires-Dist: fastapi>=0.115.2
Requires-Dist: uvicorn>=0.35.0
Provides-Extra: dev
Requires-Dist: pytest>=7.0; extra == "dev"
Requires-Dist: pytest-asyncio>=0.21; extra == "dev"
Requires-Dist: pytest-cov>=4.0; extra == "dev"
Requires-Dist: black>=23.0; extra == "dev"
Requires-Dist: isort>=5.12; extra == "dev"
Requires-Dist: flake8>=6.0; extra == "dev"
Requires-Dist: mypy>=1.0; extra == "dev"
Dynamic: author
Dynamic: classifier
Dynamic: description
Dynamic: description-content-type
Dynamic: home-page
Dynamic: provides-extra
Dynamic: requires-dist
Dynamic: requires-python
Dynamic: summary
